MANIFEST.in
README.md
requirements.txt
setup.cfg
setup.py
versioneer.py
botcity/plugins/recorder/__init__.py
botcity/plugins/recorder/_version.py
botcity/plugins/recorder/plugin.py
botcity_recorder_plugin.egg-info/PKG-INFO
botcity_recorder_plugin.egg-info/SOURCES.txt
botcity_recorder_plugin.egg-info/dependency_links.txt
botcity_recorder_plugin.egg-info/requires.txt
botcity_recorder_plugin.egg-info/top_level.txt
tests/test_import.py