Metadata-Version: 2.1
Name: botcity-recorder-plugin
Version: 0.1.3
Home-page: https://bitbucket.org/botcitydev/bot-recorder-plugin-python.git
Requires-Python: >=3.7
